CHANGELOG.md
LICENSE
MANIFEST.in
README.md
setup.py
jupyter-config/jupyter_notebook_config.d/jupyter_openbis_extension.json
jupyter-config/jupyter_server_config.d/jupyter_openbis_extension.json
jupyter-openbis-server/__init__.py
jupyter-openbis-server/application.py
jupyter-openbis-server/connection.py
jupyter-openbis-server/dataset.py
jupyter-openbis-server/handlers.py
jupyter-openbis-server/main.py
jupyter-openbis-server/requirements.py
jupyter-openbis-server/sample.py
jupyter_openbis_server.egg-info/PKG-INFO
jupyter_openbis_server.egg-info/SOURCES.txt
jupyter_openbis_server.egg-info/dependency_links.txt
jupyter_openbis_server.egg-info/entry_points.txt
jupyter_openbis_server.egg-info/not-zip-safe
jupyter_openbis_server.egg-info/requires.txt
jupyter_openbis_server.egg-info/top_level.txt
openbis_connection/main.py