Metadata-Version: 2.1
Name: jupyter-openbis-server
Version: 0.4.0
Summary: Server Extension for Jupyter notebooks to connect to openBIS and download/upload datasets, inluding the notebook itself
Home-page: https://sissource.ethz.ch/sispub/jupyter-openbis-server
Author: Swen Vermeul |  ID SIS | ETH Zürich
Author-email: swen@ethz.ch
License: Apache Software License Version 2.0
Platform: UNKNOWN
Classifier: Programming Language :: Python :: 3.3
Classifier: Programming Language :: JavaScript
Classifier: License :: OSI Approved :: Apache Software License
Classifier: Operating System :: OS Independent
Requires-Python: >=3.3
